examples/__init__.py
examples/page_create.py
examples/page_delete.py
examples/page_render.py
examples/page_single.py
examples/page_update.py
examples/pages_list.py
wikijspy/__init__.py
wikijspy/api_client.py
wikijspy/configuration.py
wikijspy/api/__init__.py
wikijspy/api/analytics.py
wikijspy/api/assets.py
wikijspy/api/authentication.py
wikijspy/api/comments.py
wikijspy/api/contribute.py
wikijspy/api/groups.py
wikijspy/api/localization.py
wikijspy/api/logging.py
wikijspy/api/mail.py
wikijspy/api/navigation.py
wikijspy/api/pages.py
wikijspy/api/rendering.py
wikijspy/api/search.py
wikijspy/api/shared.py
wikijspy/api/site.py
wikijspy/api/storage.py
wikijspy/api/system.py
wikijspy/api/theming.py
wikijspy/api/users.py
wikijspy/types/__init__.py
wikijspy/types/assets_types.py
wikijspy/types/authentication_types.py
wikijspy/types/error.py
wikijspy/types/general.py
wikijspy/types/page_types.py
wikijspy/types/users_types.py
wikijspy-0.1.6.dist-info/LICENSE
wikijspy-0.1.6.dist-info/METADATA
wikijspy-0.1.6.dist-info/WHEEL
wikijspy-0.1.6.dist-info/top_level.txt
wikijspy-0.1.6.dist-info/RECORD
