Metadata-Version: 2.1
Name: wikijspy
Version: 0.1.6
Summary: A simple wikijs API wrapper
Author: WERTBON1789
Author-email: jan210404@gmx.de
License: LICENSE
License-File: LICENSE
Requires-Dist: gql (~=3.4)
Requires-Dist: requests (~=2.31)
Requires-Dist: requests-toolbelt (~=1.0)
